extinction.cpython-38-x86_64-linux-gnu.so
extinction-0.4.8.dist-info/LICENSE
extinction-0.4.8.dist-info/METADATA
extinction-0.4.8.dist-info/WHEEL
extinction-0.4.8.dist-info/top_level.txt
extinction-0.4.8.dist-info/RECORD
