Metadata-Version: 2.1
Name: extinction
Version: 0.4.8
Summary: Fast interstellar dust extinction laws
Home-page: http://github.com/kbarbary/extinction
Author: Kyle Barbary
Author-email: kylebarbary@gmail.com
License: MIT
Classifier: Development Status :: 4 - Beta
Classifier: Programming Language :: Python :: 3
Classifier: License :: OSI Approved :: MIT License
Classifier: Topic :: Scientific/Engineering :: Astronomy
Classifier: Intended Audience :: Science/Research
Requires-Python: >=3.8
License-File: LICENSE
Requires-Dist: numpy>=1.13.3
